AUTHORS
LICENSE
MANIFEST.in
README.md
setup.py
django_healthcheck.egg-info/PKG-INFO
django_healthcheck.egg-info/SOURCES.txt
django_healthcheck.egg-info/dependency_links.txt
django_healthcheck.egg-info/requires.txt
django_healthcheck.egg-info/top_level.txt
healthcheck/__init__.py
healthcheck/models.py
healthcheck/urls.py
healthcheck/views.py